gtlparser/Convert_GTL_2_GeoJSON.py
gtlparser/__init__.py
gtlparser/common.py
gtlparser/foliumap.py
gtlparser/gtl2geojson.py
gtlparser/gtlparser.py
gtlparser/test.ipynb
gtlparser-0.2.0.dist-info/licenses/LICENSE
gtlparser-0.2.0.dist-info/METADATA
gtlparser-0.2.0.dist-info/WHEEL
gtlparser-0.2.0.dist-info/entry_points.txt
gtlparser-0.2.0.dist-info/top_level.txt
gtlparser-0.2.0.dist-info/RECORD
